genome_windows_generator
