Metadata-Version: 2.1
Name: genome-windows-generator
Version: 1.1.0
Summary: ![](https://github.com/zommiommy/genome_windows_generator/workflows/Python%20package/badge.svg)
Home-page: https://github.com/zommiommy/genome_windows_generator
Author: Tommaso Fontana
Author-email: tommaso.fontana.96@gmail.com
License: MIT
Platform: UNKNOWN
Classifier: Development Status :: 3 - Alpha
Classifier: License :: OSI Approved :: MIT License
Classifier: Programming Language :: Python :: 3
Provides-Extra: test
